cortexa_sdk/__init__.py
cortexa_sdk/cli.py
cortexa_sdk/test_sdk.py
cortexa_sdk-0.2.0.dist-info/METADATA
cortexa_sdk-0.2.0.dist-info/WHEEL
cortexa_sdk-0.2.0.dist-info/entry_points.txt
cortexa_sdk-0.2.0.dist-info/top_level.txt
cortexa_sdk-0.2.0.dist-info/RECORD
