Metadata-Version: 2.4
Name: cortexa-sdk
Version: 0.2.0
Summary: User-side Python SDK for downloading datasets and assets from Cortexa. Supports project_id, label_list, and filter_by_labels parameters for YOLO and JSON export types. Use 'annotation_type' parameter (rect, polygon) for YOLO.
Author: Cortexa
Project-URL: Homepage, https://example.com
Requires-Python: >=3.8
Requires-Dist: requests
